lxmlHtml/__init__.py
lxmlHtml/html_element_proxy.py
lxmlHtml/link.py
lxmlHtml/styles.py
lxmlHtml/version.py
lxmlHtml-0.0.2.dist-info/METADATA
lxmlHtml-0.0.2.dist-info/WHEEL
lxmlHtml-0.0.2.dist-info/top_level.txt
lxmlHtml-0.0.2.dist-info/zip-safe
lxmlHtml-0.0.2.dist-info/RECORD
