Metadata-Version: 2.1
Name: lxmlHtml
Version: 0.0.2
Summary: a html parser based lxml
Home-page: https://github.com/mouday/lxmlHtml
Author: Peng Shiyu
Author-email: pengshiyuyx@gmail.com
License: MIT
Keywords: html parser,lxml,spider
Platform: UNKNOWN
Classifier: Programming Language :: Python :: 3
Classifier: Programming Language :: Python :: 3.6
